ptrace/__init__.py
ptrace/cpu_info.py
ptrace/ctypes_libc.py
ptrace/ctypes_tools.py
ptrace/disasm.py
ptrace/error.py
ptrace/func_arg.py
ptrace/func_call.py
ptrace/linux_proc.py
ptrace/logging_tools.py
ptrace/mockup.py
ptrace/os_tools.py
ptrace/process_tools.py
ptrace/profiler.py
ptrace/pydistorm.py
ptrace/signames.py
ptrace/terminal.py
ptrace/tools.py
ptrace/version.py
ptrace/binding/__init__.py
ptrace/binding/cpu.py
ptrace/binding/freebsd_struct.py
ptrace/binding/func.py
ptrace/binding/linux_struct.py
ptrace/binding/openbsd_struct.py
ptrace/debugger/__init__.py
ptrace/debugger/application.py
ptrace/debugger/backtrace.py
ptrace/debugger/breakpoint.py
ptrace/debugger/child.py
ptrace/debugger/debugger.py
ptrace/debugger/memory_mapping.py
ptrace/debugger/parse_expr.py
ptrace/debugger/process.py
ptrace/debugger/process_error.py
ptrace/debugger/process_event.py
ptrace/debugger/ptrace_signal.py
ptrace/debugger/signal_reason.py
ptrace/debugger/syscall_state.py
ptrace/syscall/__init__.py
ptrace/syscall/freebsd_constants.py
ptrace/syscall/freebsd_syscall.py
ptrace/syscall/linux_constants.py
ptrace/syscall/linux_struct.py
ptrace/syscall/names.py
ptrace/syscall/posix_arg.py
ptrace/syscall/posix_constants.py
ptrace/syscall/prototypes.py
ptrace/syscall/ptrace_syscall.py
ptrace/syscall/socketcall.py
ptrace/syscall/socketcall_constants.py
ptrace/syscall/socketcall_struct.py
ptrace/syscall/syscall_argument.py
ptrace/syscall/linux/__init__.py
ptrace/syscall/linux/aarch64.py
ptrace/syscall/linux/i386.py
ptrace/syscall/linux/powerpc32.py
ptrace/syscall/linux/powerpc64.py
ptrace/syscall/linux/x86_64.py
python_ptrace-0.9.8.data/scripts/gdb.py
python_ptrace-0.9.8.data/scripts/strace.py
python_ptrace-0.9.8.dist-info/COPYING
python_ptrace-0.9.8.dist-info/METADATA
python_ptrace-0.9.8.dist-info/WHEEL
python_ptrace-0.9.8.dist-info/top_level.txt
python_ptrace-0.9.8.dist-info/RECORD
