Metadata-Version: 1.1
Name: python-ptrace
Version: 0.9.8
Summary: python binding of ptrace
Home-page: http://python-ptrace.readthedocs.io/
Author: Victor Stinner
Author-email: UNKNOWN
License: GNU GPL v2
Download-URL: http://python-ptrace.readthedocs.io/
Platform: UNKNOWN
Classifier: Intended Audience :: Developers
Classifier: Development Status :: 4 - Beta
Classifier: Environment :: Console
Classifier: License :: OSI Approved :: GNU General Public License (GPL)
Classifier: Operating System :: OS Independent
Classifier: Natural Language :: English
Classifier: Programming Language :: Python
Classifier: Programming Language :: Python :: 3
